hwtypes/__init__.py
hwtypes/adt.py
hwtypes/adt_meta.py
hwtypes/bit_vector.py
hwtypes/bit_vector_abc.py
hwtypes/compatibility.py
hwtypes/fp_vector.py
hwtypes/fp_vector_abc.py
hwtypes/modifiers.py
hwtypes/smt_bit_vector.py
hwtypes/util.py
hwtypes/z3_bit_vector.py
hwtypes-1.1.2.dist-info/LICENSE.txt
hwtypes-1.1.2.dist-info/METADATA
hwtypes-1.1.2.dist-info/WHEEL
hwtypes-1.1.2.dist-info/top_level.txt
hwtypes-1.1.2.dist-info/RECORD
