Metadata-Version: 2.1
Name: hwtypes
Version: 1.1.2
Summary: Python implementations of fixed size hardware types (Bit, BitVector, UInt, SInt, ...) based on the SMT-LIB2 semantics
Home-page: https://github.com/leonardt/hwtypes
Author: Leonard Truong
Author-email: lenny@cs.stanford.edu
License: UNKNOWN
Platform: UNKNOWN
Requires-Dist: pysmt
Requires-Dist: z3-solver
Requires-Dist: gmpy2
